cassava/__init__.py
cassava/__main__.py
cassava_csv-0.4.0.dist-info/entry_points.txt
cassava_csv-0.4.0.dist-info/LICENSE
cassava_csv-0.4.0.dist-info/WHEEL
cassava_csv-0.4.0.dist-info/METADATA
cassava_csv-0.4.0.dist-info/RECORD
