Metadata-Version: 2.1
Name: cassava-csv
Version: 0.4.0
Summary: Cassava is a package for reading, plotting and quality-checking CSV files.
Home-page: https://github.com/paul-breen/cassava
License: Apache-2.0
Author: Paul Breen
Author-email: pbree@bas.ac.uk
Requires-Python: >=3.7,<4.0
Classifier: License :: OSI Approved :: Apache Software License
Classifier: Programming Language :: Python :: 3
Classifier: Programming Language :: Python :: 3.7
Classifier: Programming Language :: Python :: 3.8
Classifier: Programming Language :: Python :: 3.9
Classifier: Programming Language :: Python :: 3.10
Classifier: Programming Language :: Python :: 3.11
Requires-Dist: blessed (>=1.18.1,<2.0.0)
Requires-Dist: matplotlib (>=3.4.3,<4.0.0)
Project-URL: Documentation, https://raw.githubusercontent.com/paul-breen/cassava/main/README.md
Project-URL: Repository, https://github.com/paul-breen/cassava
